{
  "서울대학교": {
    "컴퓨터공학": {
      "핵심역량": ["논리적 사고력", "수리적 추론능력", "창의적 알고리즘 설계능력", "연구 기반 문제해결력"],
      "세특패턴": [
        "프로그래밍 세특에서 단순 기능 구현이 아닌 알고리즘 원리를 논리적으로 설명",
        "수학(미적분, 기하, 확통) 개념을 활용해 문제 해결 과정을 구조화함",
        "자료구조, 컴퓨터 구조, 운영체제 개념을 스스로 확장하여 탐구한 흔적",
        "복잡한 문제를 단계별 논증 구조로 분석하는 능력이 드러남"
      ],
      "탐구·프로젝트 패턴": [
        "알고리즘 기반 문제 해결 프로젝트 수행",
        "데이터 수집·전처리·모델링 전 과정을 체계적으로 수행한 이력",
        "프로그래밍 언어를 활용해 연구 모형을 제작하거나 실험한 경험",
        "성능 분석·복잡도 비교 등 학문적 접근이 포함된 프로젝트"
      ],
      "독서 패턴": [
        "컴퓨터과학 개론 및 알고리즘 이론서",
        "인공지능·데이터과학 기초 개념서",
        "기술철학·디지털 윤리 관련 확장 독서"
      ],
      "비교과 패턴": [
        "SW·정보 탐구 동아리에서 지속적인 연구 활동",
        "해커톤, 알고리즘 경진대회 참여 경험",
        "탐구 보고서 중심의 자기주도 연구"
      ],
      "활동 구조": [
        "문제 정의 → 기존 연구 분석 → 알고리즘 설계 → 구현 → 성능 분석 → 개선 제안"
      ],
      "평가 포인트": [
        "논리·수리 기반의 엄밀한 사고력",
        "탐구 설계 능력 및 알고리즘적 사고",
        "연구자의 관점에서 문제를 정의하고 해결하는 능력"
      ]
    },

    "전기전자공학": {
      "핵심역량": ["물리 기반 이해력", "미적분·벡터 기반 모델링 능력", "회로·신호 분석력"],
      "세특패턴": [
        "물리 전자기 개념을 자기주도적으로 확장·적용",
        "회로 실험에서 데이터 분석 및 오차 해석을 정교하게 수행",
        "전기·전자 개념을 수학적 모델링과 연결하는 능력",
        "반도체 동작 원리 또는 신호 처리 개념 탐구"
      ],
      "탐구·프로젝트 패턴": [
        "아두이노·센서 기반 회로 제작 프로젝트",
        "아날로그/디지털 신호 비교 분석 연구",
        "반도체·전기장·전자기파 관련 실험 보고서 작성"
      ],
      "독서 패턴": [
        "반도체·회로이론 기초서",
        "전자기학 입문서",
        "미래공학·첨단산업 관련 확장 독서"
      ],
      "비교과 패턴": [
        "과학탐구반 실험 중심 활동",
        "전기전자 관련 R&E 참여",
        "전공 관련 실험·보고서 지속 수행"
      ],
      "활동 구조": ["가설 설정 → 실험 설계 → 측정 → 데이터 분석 → 모델 구축"],
      "평가 포인트": [
        "정확한 데이터 해석력",
        "수리·물리 기반 설계 능력",
        "과정 중심의 탐구 성실성"
      ]
    },

    "기계공학": {
      "핵심역량": ["역학적 사고력", "시스템 설계 능력", "창의적 문제 해결력"],
      "세특패턴": [
        "물리 역학 개념을 문제 해결에 적용",
        "구조·재료·동역학 중심의 과학적 탐구 수행",
        "특정 현상을 수학적 모델이나 그래프로 표현",
        "설계·제작 과정에서 근거 기반 의사결정 수행"
      ],
      "탐구·프로젝트 패턴": [
        "로봇·드론·자동차 등 기계 시스템 설계 프로젝트",
        "CAD·3D 모델링을 활용한 제작 및 분석",
        "실험 데이터를 통한 구조적 안정성 검증"
      ],
      "독서 패턴": [
        "기계공학 개론",
        "로봇·자동화 시스템 관련 독서",
        "기술혁신·미래공학 분야 확장 독서"
      ],
      "비교과 패턴": [
        "메이커 활동 또는 설계 동아리 활동",
        "공학적 실험 및 제작 경험",
        "연구 기반 프로젝트"
      ],
      "활동 구조": ["문제 분석 → 설계 → 제작 → 실험 → 피드백"],
      "평가 포인트": ["설계 사고력", "역학적 직관", "공학적 타당성"]
    },

    "화학·화학공학": {
      "핵심역량": ["분자·반응 이해력", "실험·분석 능력", "정량적 사고"],
      "세특패턴": [
        "반응속도·평형·전기화학 등 심화 개념 탐구",
        "실험 데이터의 정량적 분석 및 오차 해석",
        "화학 현상을 공정·공학적 시각에서 확장",
        "수학적 모델링 기반 탐구"
      ],
      "탐구·프로젝트 패턴": [
        "환경·에너지 화학 실험",
        "촉매·재료·고분자 특성 분석",
        "반응 조건 변화에 따른 결과 비교 연구"
      ],
      "독서 패턴": [
        "화학 개론 및 물리화학·유기화학 서적",
        "에너지·환경공학 관련 독서"
      ],
      "비교과 패턴": [
        "과학실험반 중심 연구",
        "탐구 보고서 다수 작성",
        "실험에서의 안전·정확성"
      ],
      "활동 구조": ["가설 → 실험 → 분석 → 결론 → 확장"],
      "평가 포인트": ["실험의 정교함", "자료 해석 능력", "반응 메커니즘 이해"]
    },

    "생명과학·생명공학": {
      "핵심역량": ["생명현상 이해력", "분석적 탐구능력", "연구 설계 능력"],
      "세특패턴": [
        "세포·유전·단백질 구조·대사 과정 등 심화 탐구",
        "실험 보고서에서 과정·해석·결론이 논리적으로 정리",
        "전공적 관점에서 생명 현상을 모델링하려는 시도",
        "바이오헬스·바이오텍 확장 탐구"
      ],
      "탐구·프로젝트 패턴": [
        "미생물 배양 실험",
        "효소 활성 분석",
        "CRISPR·유전자 발현 기초 이해 등 전공 탐색 프로젝트"
      ],
      "독서 패턴": [
        "생명과학 개론, 분자생물학 도서",
        "의학·바이오 산업 관련 확장 독서"
      ],
      "비교과 패턴": [
        "생명탐구반 활동",
        "연구보고서 또는 R&E 경험",
        "생명 관련 학술 행사 참여"
      ],
      "활동 구조": ["관찰 → 실험 → 분석 → 모델링"],
      "평가 포인트": ["과정 중심 탐구력", "분석력", "과학적 태도"]
    },

    "의치약한수": {
      "핵심역량": ["과학적 사고력", "윤리성", "공감능력", "학업집중력"],
      "세특패턴": [
        "생명·화학 중심의 정교한 실험 탐구",
        "의학적 관점을 적용한 문제 재구성",
        "과학적 근거 기반의 진단 및 해결책 제시"
      ],
      "탐구·프로젝트 패턴": [
        "혈액·효소·조직 관련 생명 실험",
        "보건·의학적 시각에서 지역사회 문제 분석"
      ],
      "독서 패턴": [
        "의학·윤리·생명공학 관련 도서",
        "의료인 전문성 관련 에세이 독서"
      ],
      "비교과 패턴": [
        "봉사에서 공감능력과 배려심 확인",
        "성실성·책임감 강조되는 활동"
      ],
      "활동 구조": ["관찰 → 진단 → 해결 방안 제시"],
      "평가 포인트": ["윤리적 태도", "탐구의 깊이", "타인 배려"]
    },

    "간호학": {
      "핵심역량": ["돌봄·공감", "대인관계 능력", "실천적 문제 해결력"],
      "세특패턴": [
        "생명과학 기반의 보건·건강 탐구",
        "지역사회 보건 문제를 분석하는 관점",
        "복지·건강·영양 관련 통합 탐구"
      ],
      "탐구·프로젝트 패턴": [
        "건강 격차 분석",
        "지역 보건 문제 해결 프로젝트"
      ],
      "독서 패턴": [
        "보건·간호 인문학 도서",
        "사회복지·공감 기반 서적"
      ],
      "비교과 패턴": [
        "지속적인 돌봄·봉사활동",
        "책임감이 드러나는 리더십 경험"
      ],
      "활동 구조": ["관찰 → 분석 → 실천"],
      "평가 포인트": ["공감능력", "책임감", "윤리적 태도"]
    },

    "건축학": {
      "핵심역량": ["공간 감각", "설계력", "창의적 구조 이해"],
      "세특패턴": [
        "구조·재료에 대한 과학적 접근",
        "도시·환경 문제를 공간적으로 분석",
        "설계 과정에서 논리적 선택 근거 제시"
      ],
      "탐구·프로젝트 패턴": [
        "건축 모형 제작",
        "도시 공간 분석 프로젝트"
      ],
      "독서 패턴": [
        "건축사, 건축이론, 도시환경 관련 독서"
      ],
      "비교과 패턴": [
        "미술·디자인 활동",
        "공간·구조 탐구 프로젝트"
      ],
      "활동 구조": ["문제 정의 → 설계 → 제작"],
      "평가 포인트": ["창의성", "논리적 설계", "구조 이해"]
    },

    "데이터사이언스": {
      "핵심역량": ["수리적 사고력", "논리적 분석력", "모델링 능력"],
      "세특패턴": [
        "데이터 기반 문제 정의",
        "통계·확률 활용",
        "수학적 모델링 시도"
      ],
      "탐구·프로젝트 패턴": [
        "데이터 수집·분석 프로젝트",
        "시각화 기반 보고서 작성"
      ],
      "독서 패턴": [
        "데이터과학 개론",
        "AI 철학·데이터 윤리 독서"
      ],
      "비교과 패턴": [
        "정보·수학 동아리 활동",
        "데이터 기반 탐구 발표"
      ],
      "활동 구조": ["자료 → 분석 → 모델 → 결론"],
      "평가 포인트": ["정확성", "논리성", "추론 능력"]
    },

    "AI·인공지능": {
      "핵심역량": ["추론 능력", "창의적 모델링", "수학 기반 사고"],
      "세특패턴": [
        "AI 개념의 논리적 확장",
        "수학적 계산·모델링 경험"
      ],
      "탐구·프로젝트 패턴": [
        "머신러닝 실험",
        "알고리즘 실험 비교"
      ],
      "독서 패턴": ["AI 개론", "뇌과학", "미래사회 관련 도서"],
      "비교과 패턴": ["SW 캠프", "AI 프로젝트"],
      "활동 구조": ["문제 → 모델 구성 → 실험"],
      "평가 포인트": ["창의적 사고", "모델 해석 능력"]
    },

    "바이오메디컬공학": {
      "핵심역량": ["융합적 사고력", "생명·공학 통합 분석력"],
      "세특패턴": [
        "생명 구조 분석 + 공학적 해석",
        "의공학적 기기·시스템 탐구"
      ],
      "탐구·프로젝트 패턴": [
        "바이오센서 분석",
        "의료기기 동작 원리 탐구"
      ],
      "독서 패턴": [
        "생명공학, 의료기술",
        "생체 신호 분석 관련 독서"
      ],
      "비교과 패턴": ["연구 활동", "융합 프로젝트"],
      "활동 구조": ["관찰 → 분석 → 모델링"],
      "평가 포인트": ["융합 능력"]
    },

    "로봇공학": {
      "핵심역량": ["설계·제작 능력", "제어·알고리즘 사고"],
      "세특패턴": [
        "역학·프로그래밍 통합 탐구",
        "로봇 구조 설계 근거 제시"
      ],
      "탐구·프로젝트 패턴": [
        "센서 기반 로봇 제작",
        "제어 알고리즘 비교 실험"
      ],
      "독서 패턴": ["로봇공학 개론", "공학·미래산업"],
      "비교과 패턴": ["메이커 활동", "로봇 제작 동아리"],
      "활동 구조": ["설계 → 제작 → 실험 → 개선"],
      "평가 포인트": ["공학적 사고", "창의적 문제 해결"]
    },

    "경영학": {
      "핵심역량": ["전략적 사고", "분석력", "리더십"],
      "세특패턴": [
        "경영·경제 개념을 실제 사례에 적용",
        "토론·발표 중심 탐구",
        "데이터 기반 의사결정 과정 제시"
      ],
      "탐구·프로젝트 패턴": [
        "시장 조사",
        "경영 전략 분석"
      ],
      "독서 패턴": ["경영, 인문사회, 심리학"],
      "비교과 패턴": ["학생회·리더십 활동", "프로젝트 운영 경험"],
      "활동 구조": ["문제 → 분석 → 전략"],
      "평가 포인트": ["논리적 설명력", "주도성"]
    },

    "경제학": {
      "핵심역량": ["수리적 모델링", "논증력", "비판적 분석력"],
      "세특패턴": [
        "경제 개념의 논리적 적용",
        "수학 기반 경제 모델 해석",
        "시사 경제 분석 탐구"
      ],
      "탐구·프로젝트 패턴": [
        "데이터 기반 경제 분석",
        "정책 비교 보고서"
      ],
      "독서 패턴": ["경제 이론서", "행동경제학"],
      "비교과 패턴": ["토론대회", "시사 탐구"],
      "활동 구조": ["자료 → 분석 → 가설 → 결론"],
      "평가 포인트": ["논증력", "자료 해석력"]
    },

    "교육학": {
      "핵심역량": ["관찰력", "소통력", "성찰력"],
      "세특패턴": [
        "교육철학 탐구",
        "학습자 분석 기반 보고서"
      ],
      "탐구·프로젝트 패턴": [
        "학습 유형 분석",
        "수업 설계 실험"
      ],
      "독서 패턴": ["교육학, 심리학"],
      "비교과 패턴": ["멘토링", "봉사"],
      "활동 구조": ["관찰 → 분석 → 개선"],
      "평가 포인트": ["성찰", "소통력"]
    },

    "심리학": {
      "핵심역량": ["관찰력", "공감", "분석력"],
      "세특패턴": [
        "심리 실험 설계",
        "행동 분석 탐구"
      ],
      "탐구·프로젝트 패턴": [
        "심리 실험",
        "상담 기법 탐구"
      ],
      "독서 패턴": ["심리학 이론서"],
      "비교과 패턴": ["상담 동아리", "봉사"],
      "활동 구조": ["관찰 → 해석"],
      "평가 포인트": ["통찰력"]
    },

    "사회·행정학": {
      "핵심역량": ["사회 분석력", "정책 이해", "비판적 사고"],
      "세특패턴": [
        "사회 현상 분석",
        "정책·행정 개념 탐구"
      ],
      "탐구·프로젝트 패턴": [
        "사회 문제 해결 프로젝트",
        "지역사회 분석"
      ],
      "독서 패턴": ["사회학, 행정학"],
      "비교과 패턴": ["토론 활동", "시사 탐구"],
      "활동 구조": ["문제 → 분석"],
      "평가 포인트": ["분석력"]
    },

    "정치외교학": {
      "핵심역량": ["국제문제 이해", "논리·소통", "전략적 사고"],
      "세특패턴": [
        "국제 관계 분석",
        "사례 기반 갈등 해결 탐구"
      ],
      "탐구·프로젝트 패턴": [
        "모의 UN",
        "외교 정책 비교 분석"
      ],
      "독서 패턴": ["정치학, 외교학"],
      "비교과 패턴": ["토론", "시사 연구"],
      "활동 구조": ["문제 → 협상"],
      "평가 포인트": ["설득력", "논리성"]
    },

    "언론·미디어·커뮤니케이션학과": {
      "핵심역량": ["소통력", "비판적 사고", "콘텐츠 제작 능력"],
      "세특패턴": [
        "미디어 구조 분석",
        "커뮤니케이션 이론 적용 탐구"
      ],
      "탐구·프로젝트 패턴": [
        "영상 제작",
        "미디어 리터러시 연구"
      ],
      "독서 패턴": ["미디어학, 사회학"],
      "비교과 패턴": ["방송반 활동"],
      "활동 구조": ["기획 → 제작"],
      "평가 포인트": ["창의성", "소통력"]
    },

    "디자인학": {
      "핵심역량": ["창의성", "시각적 사고"],
      "세특패턴": ["디자인 원리 탐구", "작품 분석"],
      "탐구·프로젝트 패턴": ["디자인 제작", "기획 프로젝트"],
      "독서 패턴": ["예술·디자인"],
      "비교과 패턴": ["미술 활동"],
      "활동 구조": ["기획 → 제작"],
      "평가 포인트": ["표현력"]
    }
  }
}
